Workbook

Sheet Test Cases
A1: POS System backend: API test cases
A2: Expected status codes are assumptions from the endpoint docs. Fill the blue columns (Actual status, Result) after each Postman run.
A4: Test ID | B4: Module | C4: Test case | D4: Type | E4: Method | F4: Endpoint | G4: Role / token | H4: Key request data | I4: Expected status (assumed) | J4: Expected result | K4: Actual status | L4: Result | M4: Source | N4: Notes
A5: AUT-01 | B5: Auth | C5: Sign up a store admin | D5: Positive | E5: POST | F5: /auth/signup | G5: None (public) | H5: fullName, email, password, username, role=ROLE_STORE_ADMIN | I5: 200 or 201 | J5: User created and JWT returned | L5: Not run | M5: Postman
A6: AUT-02 | B6: Auth | C6: Sign in with valid credentials | D6: Positive | E6: POST | F6: /auth/login | G6: None (public) | H6: email, password | I6: 200 | J6: JWT and user data returned | L6: Not run | M6: Postman
A7: AUT-03 | B7: Auth | C7: Get own profile | D7: Positive | E7: GET | F7: /api/users/profile | G7: Store Admin ({{store_admin_jwt}}) | H7: Bearer token | I7: 200 | J7: Profile with role returned | L7: Not run | M7: Postman
A8: AUT-04 | B8: Auth | C8: Get all users | D8: Positive | E8: GET | F8: /users/list | G8: Admin (admin token) | H8: Bearer token | I8: 200 | J8: List of users returned | L8: Not run | M8: Postman | N8: Postman uses {{jwt2}}. Path has no /api prefix, same as the frontend.
A9: AUT-05 | B9: Auth | C9: Sign up with an existing email | D9: Negative | E9: POST | F9: /auth/signup | G9: None (public) | H9: email already registered | I9: 400 or 409 | J9: Error message, no duplicate user | L9: Not run | M9: Added (negative / security)
A10: AUT-06 | B10: Auth | C10: Sign up with invalid email and short password | D10: Negative | E10: POST | F10: /auth/signup | G10: None (public) | H10: email=abc, password=1 | I10: 400 | J10: Validation error | L10: Not run | M10: Added (negative / security)
A11: AUT-07 | B11: Auth | C11: Sign up with role ROLE_ADMIN | D11: Negative | E11: POST | F11: /auth/signup | G11: None (public) | H11: role=ROLE_ADMIN | I11: 400 or 403 | J11: Request rejected, no admin created | L11: Not run | M11: Added (negative / security) | N11: Public signup currently accepts a role field. Make sure admin cannot be self-assigned.
A12: AUT-08 | B12: Auth | C12: Sign in with wrong password | D12: Negative | E12: POST | F12: /auth/login | G12: None (public) | H12: valid email, wrong password | I12: 400 or 401 | J12: Error message, no token | L12: Not run | M12: Added (negative / security)
A13: AUT-09 | B13: Auth | C13: Call a protected endpoint without a token | D13: Negative | E13: GET | F13: /api/users/profile | G13: None (public) | H13: No Authorization header | I13: 401 or 403 | J13: Access denied | L13: Not run | M13: Added (negative / security)
A14: AUT-10 | B14: Auth | C14: Request a password reset email | D14: Positive | E14: POST | F14: /auth/forgot-password | G14: None (public) | H14: email | I14: 200 | J14: Reset email sent | L14: Not run | M14: Added (not in Postman yet)
A15: AUT-11 | B15: Auth | C15: Reset password with a valid token | D15: Positive | E15: POST | F15: /auth/reset-password | G15: None (public) | H15: token, password | I15: 200 | J15: Password changed | L15: Not run | M15: Added (not in Postman yet)
A16: AUT-12 | B16: Auth | C16: Reset password with an invalid token | D16: Negative | E16: POST | F16: /auth/reset-password | G16: None (public) | H16: token=invalid, password | I16: 400 | J16: Error message | L16: Not run | M16: Added (not in Postman yet)
A17: STO-01 | B17: Store | C17: Create a store | D17: Positive | E17: POST | F17: /api/stores | G17: Store Admin ({{store_admin_jwt}}) | H17: brand, storeType, contact(address, email, phone), description | I17: 200 or 201 | J17: Store created with status PENDING | L17: Not run | M17: Postman
A18: STO-02 | B18: Store | C18: Get store of the logged-in employee | D18: Positive | E18: GET | F18: /api/stores/employee | G18: Store Manager ({{store_manager_jwt}}) | H18: Bearer token | I18: 200 | J18: Store returned | L18: Not run | M18: Postman
A19: STO-03 | B19: Store | C19: Get store of the logged-in admin | D19: Positive | E19: GET | F19: /api/stores/admin | G19: Store Admin ({{store_admin_jwt}}) | H19: Bearer token | I19: 200 | J19: Store returned | L19: Not run | M19: Postman
A20: STO-04 | B20: Store | C20: Update a store | D20: Positive | E20: PUT | F20: /api/stores/1 | G20: Store Admin ({{store_admin_jwt}}) | H20: brand, description, storeType, contact | I20: 200 | J20: Updated store returned | L20: Not run | M20: Postman
A21: STO-05 | B21: Store | C21: Get a store that does not exist | D21: Negative | E21: GET | F21: /api/stores/9999 | G21: Store Admin ({{store_admin_jwt}}) | H21: id=9999 | I21: 404 | J21: Not found message | L21: Not run | M21: Added (negative / security)
A22: STO-06 | B22: Store | C22: Get all stores filtered by status | D22: Positive | E22: GET | F22: /api/stores?status=PENDING | G22: Admin (admin token) | H22: status=PENDING | I22: 200 | J22: List of pending stores | L22: Not run | M22: Added (not in Postman yet)
A23: STO-07 | B23: Store | C23: Approve a store | D23: Positive | E23: PUT | F23: /api/stores/1/moderate?action=APPROVED | G23: Admin (admin token) | H23: action=APPROVED | I23: 200 | J23: Store status updated | L23: Not run | M23: Added (not in Postman yet)
A24: BRA-01 | B24: Branch | C24: Create a branch | D24: Positive | E24: POST | F24: /api/branches | G24: Store Admin ({{store_admin_jwt}}) | H24: name, address, workingDays | I24: 200 or 201 | J24: Branch created | L24: Not run | M24: Postman
A25: BRA-02 | B25: Branch | C25: List employees of a branch | D25: Positive | E25: GET | F25: /api/branches/1/employee/list | G25: Branch Manager ({{branch_manager_jwt}}) | H25: Bearer token | I25: 200 | J25: Employees returned | L25: Not run | M25: Postman | N25: Employee docs use /api/employees/branch/{id}. Check which path exists.
A26: BRA-03 | B26: Branch | C26: Get all branches of a store | D26: Positive | E26: GET | F26: /api/branches/store/1 | G26: Store Admin ({{store_admin_jwt}}) | H26: storeId=1 | I26: 200 | J26: Branch list returned | L26: Not run | M26: Postman | N26: Same request also appears in the Store folder.
A27: BRA-04 | B27: Branch | C27: Get a branch by id | D27: Positive | E27: GET | F27: /api/branches/1 | G27: Store Admin ({{store_admin_jwt}}) | H27: id=1 | I27: 200 | J27: Branch returned | L27: Not run | M27: Postman
A28: BRA-05 | B28: Branch | C28: Update a branch | D28: Positive | E28: PUT | F28: /api/branches/1 | G28: Store Admin ({{store_admin_jwt}}) | H28: name, address, workingDays, openTime, closeTime | I28: 200 | J28: Updated branch returned | L28: Not run | M28: Postman
A29: BRA-06 | B29: Branch | C29: Delete a branch | D29: Positive | E29: DELETE | F29: /api/branches/1 | G29: Store Admin ({{store_admin_jwt}}) | H29: id=1 | I29: 200 or 204 | J29: Branch removed | L29: Not run | M29: Added (not in Postman yet)
A30: CAT-01 | B30: Category | C30: Create a category | D30: Positive | E30: POST | F30: /api/categories | G30: Store Admin ({{store_admin_jwt}}) | H30: storeId=1, name=shoes | I30: 200 or 201 | J30: Category created | L30: Not run | M30: Postman
A31: CAT-02 | B31: Category | C31: Get categories of a store | D31: Positive | E31: GET | F31: /api/categories/store/1 | G31: Store Admin ({{store_admin_jwt}}) | H31: storeId=1 | I31: 200 | J31: Category list returned | L31: Not run | M31: Postman
A32: CAT-03 | B32: Category | C32: Update a category | D32: Positive | E32: PUT | F32: /api/categories/1 | G32: Store Admin ({{store_admin_jwt}}) | H32: name=pants | I32: 200 | J32: Updated category returned | L32: Not run | M32: Postman
A33: CAT-04 | B33: Category | C33: Delete a category | D33: Positive | E33: DELETE | F33: /api/categories/1 | G33: Store Admin ({{store_admin_jwt}}) | H33: id=1 | I33: 200 or 204 | J33: Category removed | L33: Not run | M33: Added (not in Postman yet)
A34: CAT-05 | B34: Category | C34: Create a category as a cashier | D34: Negative | E34: POST | F34: /api/categories | G34: Cashier ({{cashier_jwt}}) | H34: storeId=1, name | I34: 403 | J34: Access denied | L34: Not run | M34: Added (negative / security) | N34: Only store manager and store admin should create categories.
A35: PRO-01 | B35: Product | C35: Create a product | D35: Positive | E35: POST | F35: /api/products | G35: Store Admin ({{store_admin_jwt}}) | H35: name, sku, mrp, sellingPrice, brand, categoryId, storeId, image | I35: 200 or 201 | J35: Product created | L35: Not run | M35: Postman
A36: PRO-02 | B36: Product | C36: Get products of a store | D36: Positive | E36: GET | F36: /api/products/store/1 | G36: Store Admin ({{store_admin_jwt}}) | H36: storeId=1 | I36: 200 | J36: Product list returned | L36: Not run | M36: Postman
A37: PRO-03 | B37: Product | C37: Update a product | D37: Positive | E37: PATCH | F37: /api/products/1 | G37: Store Admin ({{store_admin_jwt}}) | H37: name, sku, mrp, sellingPrice, categoryId | I37: 200 | J37: Updated product returned | L37: Not run | M37: Postman
A38: PRO-04 | B38: Product | C38: Get a product by id | D38: Positive | E38: GET | F38: /api/products/1 | G38: Store Admin ({{store_admin_jwt}}) | H38: id=1 | I38: 200 | J38: Product returned | L38: Not run | M38: Added (not in Postman yet)
A39: PRO-05 | B39: Product | C39: Search products in a store | D39: Positive | E39: GET | F39: /api/products/store/1/search?q=shoes | G39: Cashier ({{cashier_jwt}}) | H39: q=shoes | I39: 200 | J39: Matching products returned | L39: Not run | M39: Added (not in Postman yet)
A40: PRO-06 | B40: Product | C40: Delete a product | D40: Positive | E40: DELETE | F40: /api/products/1 | G40: Store Admin ({{store_admin_jwt}}) | H40: id=1 | I40: 200 or 204 | J40: Product removed | L40: Not run | M40: Added (not in Postman yet)
A41: PRO-07 | B41: Product | C41: Create a product with a duplicate SKU | D41: Negative | E41: POST | F41: /api/products | G41: Store Admin ({{store_admin_jwt}}) | H41: existing sku | I41: 400 or 409 | J41: Error message | L41: Not run | M41: Added (negative / security)
A42: PRO-08 | B42: Product | C42: Create a product as a cashier | D42: Negative | E42: POST | F42: /api/products | G42: Cashier ({{cashier_jwt}}) | H42: valid product data | I42: 403 | J42: Access denied | L42: Not run | M42: Added (negative / security)
A43: ORD-01 | B43: Order | C43: Create an order | D43: Positive | E43: POST | F43: /api/orders | G43: Cashier ({{cashier_jwt}}) | H43: customer, items(productId, quantity), paymentType=UPI | I43: 200 or 201 | J43: Order created with total and items | L43: Not run | M43: Postman | N43: Frontend adds 18% tax in the cart. Check the saved totalAmount.
A44: ORD-02 | B44: Order | C44: Get orders of a branch | D44: Positive | E44: GET | F44: /api/orders/branch/1 | G44: Branch Manager ({{branch_manager_jwt}}) | H44: branchId=1 | I44: 200 | J44: Order list returned | L44: Not run | M44: Postman
A45: ORD-03 | B45: Order | C45: Get orders of a cashier | D45: Positive | E45: GET | F45: /api/orders/cashier/102 | G45: Cashier ({{cashier_jwt}}) | H45: cashierId=102 | I45: 200 | J45: Order list returned | L45: Not run | M45: Postman
A46: ORD-04 | B46: Order | C46: Get orders of a branch with filters | D46: Positive | E46: GET | F46: /api/orders/branch/1?paymentType=UPI | G46: Cashier ({{cashier_jwt}}) | H46: paymentType=UPI | I46: 200 | J46: Filtered orders returned | L46: Not run | M46: Postman | N46: Postman sends a request body on this GET. Remove it.
A47: ORD-05 | B47: Order | C47: Get today's orders of a branch | D47: Positive | E47: GET | F47: /api/orders/today/branch/1 | G47: Cashier ({{cashier_jwt}}) | H47: branchId=1 | I47: 200 | J47: Today's orders returned | L47: Not run | M47: Postman
A48: ORD-06 | B48: Order | C48: Get the 5 most recent orders of a branch | D48: Positive | E48: GET | F48: /api/orders/recent/1 | G48: Branch Manager ({{branch_manager_jwt}}) | H48: branchId=1 | I48: 200 | J48: 5 recent orders returned | L48: Not run | M48: Postman | N48: Postman uses {{cashier_jwt}}, but docs allow only branch manager and branch admin.
A49: ORD-07 | B49: Order | C49: Get recent orders as a cashier | D49: Negative | E49: GET | F49: /api/orders/recent/1 | G49: Cashier ({{cashier_jwt}}) | H49: branchId=1 | I49: 403 | J49: Access denied | L49: Not run | M49: Added (negative / security)
A50: ORD-08 | B50: Order | C50: Create an order with more quantity than stock | D50: Negative | E50: POST | F50: /api/orders | G50: Cashier ({{cashier_jwt}}) | H50: quantity above inventory | I50: 400 | J50: Out of stock error, stock unchanged | L50: Not run | M50: Added (negative / security)
A51: ORD-09 | B51: Order | C51: Get orders of a customer | D51: Positive | E51: GET | F51: /api/orders/customer/1 | G51: Cashier ({{cashier_jwt}}) | H51: customerId=1 | I51: 200 | J51: Order list returned | L51: Not run | M51: Added (not in Postman yet)
A52: ORD-10 | B52: Order | C52: Delete an order | D52: Positive | E52: DELETE | F52: /api/orders/1 | G52: Store Manager ({{store_manager_jwt}}) | H52: id=1 | I52: 200 or 204 | J52: Order removed | L52: Not run | M52: Added (not in Postman yet)
A53: EMP-01 | B53: Employee | C53: List employees of a store | D53: Positive | E53: GET | F53: /api/employees/store/1 | G53: Store Admin ({{store_admin_jwt}}) | H53: storeId=1 | I53: 200 | J53: Employee list returned | L53: Not run | M53: Postman
A54: EMP-02 | B54: Employee | C54: List employees of a branch | D54: Positive | E54: GET | F54: /api/employees/branch/1 | G54: Store Admin ({{store_admin_jwt}}) | H54: branchId=1 | I54: 200 | J54: Employee list returned | L54: Not run | M54: Postman
A55: EMP-03 | B55: Employee | C55: Add a branch manager to a store | D55: Positive | E55: POST | F55: /api/employees/store/1 | G55: Store Admin ({{store_admin_jwt}}) | H55: email, password, fullName, role=ROLE_BRANCH_MANAGER, branchId | I55: 200 or 201 | J55: Employee created | L55: Not run | M55: Postman
A56: EMP-04 | B56: Employee | C56: Add a cashier to a branch | D56: Positive | E56: POST | F56: /api/employees/branch/1 | G56: Store Admin ({{store_admin_jwt}}) | H56: email, password, fullName, role=ROLE_BRANCH_CASHIER | I56: 200 or 201 | J56: Cashier created | L56: Not run | M56: Postman
A57: EMP-05 | B57: Employee | C57: Update an employee | D57: Positive | E57: PUT | F57: /api/employees/1 | G57: Store Admin ({{store_admin_jwt}}) | H57: fullName, phone | I57: 200 | J57: Updated employee returned | L57: Not run | M57: Added (not in Postman yet)
A58: EMP-06 | B58: Employee | C58: Delete an employee | D58: Positive | E58: DELETE | F58: /api/employees/1 | G58: Store Admin ({{store_admin_jwt}}) | H58: id=1 | I58: 200 or 204 | J58: Employee removed | L58: Not run | M58: Added (not in Postman yet)
A59: INV-01 | B59: Inventory | C59: Create an inventory record | D59: Positive | E59: POST | F59: /api/inventories | G59: Store Admin ({{store_admin_jwt}}) | H59: productId=1, branchId=1, quantity=100 | I59: 200 or 201 | J59: Inventory created | L59: Not run | M59: Postman
A60: INV-02 | B60: Inventory | C60: Get stock by branch and product | D60: Positive | E60: GET | F60: /api/inventories/branch/1/product/1 | G60: Store Admin ({{store_admin_jwt}}) | H60: branchId, productId | I60: 200 | J60: Stock record returned | L60: Not run | M60: Postman
... A64: CUS-01 | B64: Customer | C64: Create a customer | D64: Positive | E64: POST | F64: /api/customers | G64: Store Admin ({{store_admin_jwt}}) | H64: fullName, phone, email | I64: 200 or 201 | J64: Customer created | L64: Not run | M64: Postman
A65: CUS-02 | B65: Customer | C65: Get all customers | D65: Positive | E65: GET | F65: /api/customers | G65: Store Admin ({{store_admin_jwt}}) | H65: Bearer token | I65: 200 | J65: Customer list returned | L65: Not run | M65: Postman | N65: Postman sends a request body on this GET. Remove it.
A66: CUS-03 | B66: Customer | C66: Search customers | D66: Positive | E66: GET | F66: /api/customers/search?q=mumbai | G66: Store Admin ({{store_admin_jwt}}) | H66: q=mumbai | I66: 200 | J66: Matching customers returned | L66: Not run | M66: Postman | N66: Postman sends a request body on this GET. Remove it.
A67: CUS-04 | B67: Customer | C67: Delete a customer | D67: Positive | E67: DELETE | F67: /api/customers/1 | G67: Store Admin ({{store_admin_jwt}}) | H67: id=1 | I67: 200 or 204 | J67: Customer removed | L67: Not run | M67: Postman
A68: CUS-05 | B68: Customer | C68: Get a customer by id | D68: Positive | E68: GET | F68: /api/customers/1 | G68: Store Admin ({{store_admin_jwt}}) | H68: id=1 | I68: 200 | J68: Customer returned | L68: Not run | M68: Added (not in Postman yet)
A69: CUS-06 | B69: Customer | C69: Update a customer | D69: Positive | E69: PUT | F69: /api/customers/1 | G69: Store Admin ({{store_admin_jwt}}) | H69: fullName, phone, email | I69: 200 | J69: Updated customer returned | L69: Not run | M69: Added (not in Postman yet)
A70: REF-01 | B70: Refund | C70: Create a refund | D70: Positive | E70: POST | F70: /api/refunds | G70: Cashier ({{cashier_jwt}}) | H70: orderId, reason, amount | I70: 200 or 201 | J70: Refund created and linked to the shift | L70: Not run | M70: Postman
A71: REF-02 | B71: Refund | C71: Get refunds of a cashier | D71: Positive | E71: GET | F71: /api/refunds/cashier/102 | G71: Cashier ({{cashier_jwt}}) | H71: cashierId=102 | I71: 200 | J71: Refund list returned | L71: Not run | M71: Postman
A72: REF-03 | B72: Refund | C72: Get refunds of a branch | D72: Positive | E72: GET | F72: /api/refunds/branch/1 | G72: Cashier ({{cashier_jwt}}) | H72: branchId=1 | I72: 200 | J72: Refund list returned | L72: Not run | M72: Postman
A73: REF-04 | B73: Refund | C73: Get a refund by id | D73: Positive | E73: GET | F73: /api/refunds/1 | G73: Cashier ({{cashier_jwt}}) | H73: id=1 | I73: 200 | J73: Refund returned | L73: Not run | M73: Postman
A74: REF-05 | B74: Refund | C74: Get all refunds | D74: Positive | E74: GET | F74: /api/refunds | G74: Cashier ({{cashier_jwt}}) | H74: Bearer token | I74: 200 | J74: Refund list returned | L74: Not run | M74: Postman
A75: REF-06 | B75: Refund | C75: Get refunds of a cashier in a date range | D75: Positive | E75: GET | F75: /api/refunds/cashier/102/range | G75: Cashier ({{cashier_jwt}}) | H75: startDate, endDate | I75: 200 | J75: Refunds in range returned | L75: Not run | M75: Postman | N75: Postman uses startDate/endDate, frontend uses from/to. Confirm the real parameter names.
A76: REF-07 | B76: Refund | C76: Refund more than the order total | D76: Negative | E76: POST | F76: /api/refunds | G76: Cashier ({{cashier_jwt}}) | H76: amount above order total | I76: 400 | J76: Error message, no refund saved | L76: Not run | M76: Added (negative / security)
A77: SHF-01 | B77: Shift Report | C77: Start a shift | D77: Positive | E77: POST | F77: /api/shift-reports/start?branchId=1 | G77: Cashier ({{cashier_jwt}}) | H77: branchId=1 | I77: 200 or 201 | J77: Shift started | L77: Not run | M77: Postman | N77: Postman sends a branch JSON body, frontend sends ?branchId=. Confirm which one the backend expects.
A78: SHF-02 | B78: Shift Report | C78: Get current shift progress | D78: Positive | E78: GET | F78: /api/shift-reports/current | G78: Cashier ({{cashier_jwt}}) | H78: Bearer token | I78: 200 | J78: Live shift totals returned | L78: Not run | M78: Postman
A79: SHF-03 | B79: Shift Report | C79: End the current shift | D79: Positive | E79: PATCH | F79: /api/shift-reports/end | G79: Cashier ({{cashier_jwt}}) | H79: Bearer token | I79: 200 | J79: Final shift report returned | L79: Not run | M79: Postman
A80: SHF-04 | B80: Shift Report | C80: Get shifts of a cashier | D80: Positive | E80: GET | F80: /api/shift-reports/cashier/102 | G80: Cashier ({{cashier_jwt}}) | H80: cashierId=102 | I80: 200 | J80: Shift list returned | L80: Not run | M80: Postman
A81: SHF-05 | B81: Shift Report | C81: Get shifts of a branch | D81: Positive | E81: GET | F81: /api/shift-reports/branch/1 | G81: Cashier ({{cashier_jwt}}) | H81: branchId=1 | I81: 200 | J81: Shift list returned | L81: Not run | M81: Postman
A82: SHF-06 | B82: Shift Report | C82: Get a shift report by date | D82: Positive | E82: GET | F82: /api/shift-reports/cashier/102/by-date | G82: Cashier ({{cashier_jwt}}) | H82: date=2025-08-02T08:27:01 | I82: 200 | J82: Shift report returned | L82: Not run | M82: Postman
A83: SHF-07 | B83: Shift Report | C83: Start a shift while one is already active | D83: Negative | E83: POST | F83: /api/shift-reports/start?branchId=1 | G83: Cashier ({{cashier_jwt}}) | H83: active shift exists | I83: 400 | J83: Error message | L83: Not run | M83: Added (negative / security)
A84: ADM-01 | B84: Admin Dashboard | C84: Get dashboard summary | D84: Positive | E84: GET | F84: /api/super-admin/dashboard/summary | G84: Admin (admin token) | H84: Bearer token | I84: 200 | J84: Total, active, pending and blocked stores | L84: Not run | M84: Postman | N84: Postman uses {{cashier_jwt}}. Use an admin token.
A85: ADM-02 | B85: Admin Dashboard | C85: Get store registrations of the last 7 days | D85: Positive | E85: GET | F85: /api/super-admin/dashboard/store-registrations | G85: Admin (admin token) | H85: Bearer token | I85: 200 | J85: 7 daily counts returned | L85: Not run | M85: Postman | N85: Postman uses {{cashier_jwt}}. Use an admin token.
A86: ADM-03 | B86: Admin Dashboard | C86: Get store status distribution | D86: Positive | E86: GET | F86: /api/super-admin/dashboard/store-status-distribution | G86: Admin (admin token) | H86: Bearer token | I86: 200 | J86: Counts per status returned | L86: Not run | M86: Postman | N86: Postman uses {{cashier_jwt}}. Use an admin token.
A87: ADM-04 | B87: Admin Dashboard | C87: Open the dashboard as a cashier | D87: Negative | E87: GET | F87: /api/super-admin/dashboard/summary | G87: Cashier ({{cashier_jwt}}) | H87: Bearer token | I87: 403 | J87: Access denied | L87: Not run | M87: Added (negative / security)
A88: ANA-01 | B88: Branch Analytics | C88: Get daily sales chart data | D88: Positive | E88: GET | F88: /api/branch-analytics/daily-sales?branchId=1 | G88: Branch Manager ({{branch_manager_jwt}}) | H88: branchId=1, days (default 7) | I88: 200 | J88: Daily sales for the last N days | L88: Not run | M88: Postman | N88: Remove the extra branchId header in Postman.
A89: ANA-02 | B89: Branch Analytics | C89: Get top products | D89: Positive | E89: GET | F89: /api/branch-analytics/top-products?branchId=1 | G89: Branch Manager ({{branch_manager_jwt}}) | H89: branchId=1 | I89: 200 | J89: Top 5 products with percentage | L89: Not run | M89: Postman
A90: ANA-03 | B90: Branch Analytics | C90: Get top cashiers | D90: Positive | E90: GET | F90: /api/branch-analytics/top-cashiers?branchId=1 | G90: Branch Manager ({{branch_manager_jwt}}) | H90: branchId=1 | I90: 200 | J90: Top 5 cashiers by revenue | L90: Not run | M90: Postman
A91: ANA-04 | B91: Branch Analytics | C91: Get category sales for a date | D91: Positive | E91: GET | F91: /api/branch-analytics/category-sales?branchId=1&date=2025-07-30 | G91: Branch Manager ({{branch_manager_jwt}}) | H91: branchId, date | I91: 200 | J91: Category-wise sales | L91: Not run | M91: Postman
A92: ANA-05 | B92: Branch Analytics | C92: Get today's overview | D92: Positive | E92: GET | F92: /api/branch-analytics/today-overview?branchId=1 | G92: Branch Manager ({{branch_manager_jwt}}) | H92: branchId=1 | I92: 200 | J92: Sales, orders and customers for today | L92: Not run | M92: Postman
A93: ANA-06 | B93: Branch Analytics | C93: Get payment breakdown for a date | D93: Positive | E93: GET | F93: /api/branch-analytics/payment-breakdown?branchId=1&date=2025-08-01 | G93: Branch Manager ({{branch_manager_jwt}}) | H93: branchId, date | I93: 200 | J93: Cash, card and UPI split | L93: Not run | M93: Postman
A94: SAN-01 | B94: Store Analytics | C94: Get store overview | D94: Positive | E94: GET | F94: /api/store/analytics/1/overview | G94: Store Admin ({{store_admin_jwt}}) | H94: storeAdminId=1 | I94: 200 | J94: KPI summary returned | L94: Not run | M94: Added (not in Postman yet)
A95: SAN-02 | B95: Store Analytics | C95: Get store alerts | D95: Positive | E95: GET | F95: /api/store/analytics/1/alerts | G95: Store Admin ({{store_admin_jwt}}) | H95: storeAdminId=1 | I95: 200 | J95: Low stock and other alerts | L95: Not run | M95: Added (not in Postman yet)
A96: SUB-01 | B96: Subscription | C96: Create a subscription plan | D96: Positive | E96: POST | F96: /api/super-admin/subscription-plans | G96: Admin (admin token) | H96: name, price, billingCycle, limits | I96: 200 or 201 | J96: Plan created | L96: Not run | M96: Added (not in Postman yet)
A97: SUB-02 | B97: Subscription | C97: Get all subscription plans | D97: Positive | E97: GET | F97: /api/super-admin/subscription-plans | G97: Admin (admin token) | H97: Bearer token | I97: 200 | J97: Plan list returned | L97: Not run | M97: Added (not in Postman yet)
A98: SUB-03 | B98: Subscription | C98: Subscribe a store to a plan | D98: Positive | E98: POST | F98: /api/subscriptions/subscribe?storeId=1&planId=1&gateway=RAZORPAY | G98: Store Admin ({{store_admin_jwt}}) | H98: storeId, planId, gateway | I98: 200 or 201 | J98: Subscription created, checkout URL returned | L98: Not run | M98: Added (not in Postman yet)
A99: SUB-04 | B99: Subscription | C99: Get subscriptions of a store | D99: Positive | E99: GET | F99: /api/subscriptions/store/1 | G99: Store Admin ({{store_admin_jwt}}) | H99: storeId=1 | I99: 200 | J99: Subscription list returned | L99: Not run | M99: Added (not in Postman yet)
A100: SUB-05 | B100: Subscription | C100: Subscribe as a cashier | D100: Negative | E100: POST | F100: /api/subscriptions/subscribe?storeId=1&planId=1 | G100: Cashier ({{cashier_jwt}}) | H100: valid ids | I100: 403 | J100: Access denied | L100: Not run | M100: Added (negative / security)

Sheet Summary
A1: Test summary
A3: Module | B3: Total | C3: Pass | D3: Fail | E3: Not run | F3: Pass rate (of run tests)
A4: Auth | B4: =COUNTIFS('Test Cases'!$B:$B,$A4) -> 12 | C4: =COUNTIFS('Test Cases'!$B:$B,$A4,'Test Cases'!$L:$L,"Pass") -> 0 | D4: =COUNTIFS('Test Cases'!$B:$B,$A4,'Test Cases'!$L:$L,"Fail") -> 0 | E4: =COUNTIFS('Test Cases'!$B:$B,$A4,'Test Cases'!$L:$L,"Not run") -> 12 | F4: =IF(C4+D4=0,"-",C4/(C4+D4)) -> -
A5: Store | B5: =COUNTIFS('Test Cases'!$B:$B,$A5) -> 7 | C5: =COUNTIFS('Test Cases'!$B:$B,$A5,'Test Cases'!$L:$L,"Pass") -> 0 | D5: =COUNTIFS('Test Cases'!$B:$B,$A5,'Test Cases'!$L:$L,"Fail") -> 0 | E5: =COUNTIFS('Test Cases'!$B:$B,$A5,'Test Cases'!$L:$L,"Not run") -> 7 | F5: =IF(C5+D5=0,"-",C5/(C5+D5)) -> -
A6: Branch | B6: =COUNTIFS('Test Cases'!$B:$B,$A6) -> 6 | C6: =COUNTIFS('Test Cases'!$B:$B,$A6,'Test Cases'!$L:$L,"Pass") -> 0 | D6: =COUNTIFS('Test Cases'!$B:$B,$A6,'Test Cases'!$L:$L,"Fail") -> 0 | E6: =COUNTIFS('Test Cases'!$B:$B,$A6,'Test Cases'!$L:$L,"Not run") -> 6 | F6: =IF(C6+D6=0,"-",C6/(C6+D6)) -> -
A7: Category | B7: =COUNTIFS('Test Cases'!$B:$B,$A7) -> 5 | C7: =COUNTIFS('Test Cases'!$B:$B,$A7,'Test Cases'!$L:$L,"Pass") -> 0 | D7: =COUNTIFS('Test Cases'!$B:$B,$A7,'Test Cases'!$L:$L,"Fail") -> 0 | E7: =COUNTIFS('Test Cases'!$B:$B,$A7,'Test Cases'!$L:$L,"Not run") -> 5 | F7: =IF(C7+D7=0,"-",C7/(C7+D7)) -> -
A8: Product | B8: =COUNTIFS('Test Cases'!$B:$B,$A8) -> 8 | C8: =COUNTIFS('Test Cases'!$B:$B,$A8,'Test Cases'!$L:$L,"Pass") -> 0 | D8: =COUNTIFS('Test Cases'!$B:$B,$A8,'Test Cases'!$L:$L,"Fail") -> 0 | E8: =COUNTIFS('Test Cases'!$B:$B,$A8,'Test Cases'!$L:$L,"Not run") -> 8 | F8: =IF(C8+D8=0,"-",C8/(C8+D8)) -> -
A9: Order | B9: =COUNTIFS('Test Cases'!$B:$B,$A9) -> 10 | C9: =COUNTIFS('Test Cases'!$B:$B,$A9,'Test Cases'!$L:$L,"Pass") -> 0 | D9: =COUNTIFS('Test Cases'!$B:$B,$A9,'Test Cases'!$L:$L,"Fail") -> 0 | E9: =COUNTIFS('Test Cases'!$B:$B,$A9,'Test Cases'!$L:$L,"Not run") -> 10 | F9: =IF(C9+D9=0,"-",C9/(C9+D9)) -> -
A10: Employee | B10: =COUNTIFS('Test Cases'!$B:$B,$A10) -> 6 | C10: =COUNTIFS('Test Cases'!$B:$B,$A10,'Test Cases'!$L:$L,"Pass") -> 0 | D10: =COUNTIFS('Test Cases'!$B:$B,$A10,'Test Cases'!$L:$L,"Fail") -> 0 | E10: =COUNTIFS('Test Cases'!$B:$B,$A10,'Test Cases'!$L:$L,"Not run") -> 6 | F10: =IF(C10+D10=0,"-",C10/(C10+D10)) -> -
A11: Inventory | B11: =COUNTIFS('Test Cases'!$B:$B,$A11) -> 5 | C11: =COUNTIFS('Test Cases'!$B:$B,$A11,'Test Cases'!$L:$L,"Pass") -> 0 | D11: =COUNTIFS('Test Cases'!$B:$B,$A11,'Test Cases'!$L:$L,"Fail") -> 0 | E11: =COUNTIFS('Test Cases'!$B:$B,$A11,'Test Cases'!$L:$L,"Not run") -> 5 | F11: =IF(C11+D11=0,"-",C11/(C11+D11)) -> -
A12: Customer | B12: =COUNTIFS('Test Cases'!$B:$B,$A12) -> 6 | C12: =COUNTIFS('Test Cases'!$B:$B,$A12,'Test Cases'!$L:$L,"Pass") -> 0 | D12: =COUNTIFS('Test Cases'!$B:$B,$A12,'Test Cases'!$L:$L,"Fail") -> 0 | E12: =COUNTIFS('Test Cases'!$B:$B,$A12,'Test Cases'!$L:$L,"Not run") -> 6 | F12: =IF(C12+D12=0,"-",C12/(C12+D12)) -> -
A13: Refund | B13: =COUNTIFS('Test Cases'!$B:$B,$A13) -> 7 | C13: =COUNTIFS('Test Cases'!$B:$B,$A13,'Test Cases'!$L:$L,"Pass") -> 0 | D13: =COUNTIFS('Test Cases'!$B:$B,$A13,'Test Cases'!$L:$L,"Fail") -> 0 | E13: =COUNTIFS('Test Cases'!$B:$B,$A13,'Test Cases'!$L:$L,"Not run") -> 7 | F13: =IF(C13+D13=0,"-",C13/(C13+D13)) -> -
A14: Shift Report | B14: =COUNTIFS('Test Cases'!$B:$B,$A14) -> 7 | C14: =COUNTIFS('Test Cases'!$B:$B,$A14,'Test Cases'!$L:$L,"Pass") -> 0 | D14: =COUNTIFS('Test Cases'!$B:$B,$A14,'Test Cases'!$L:$L,"Fail") -> 0 | E14: =COUNTIFS('Test Cases'!$B:$B,$A14,'Test Cases'!$L:$L,"Not run") -> 7 | F14: =IF(C14+D14=0,"-",C14/(C14+D14)) -> -
A15: Admin Dashboard | B15: =COUNTIFS('Test Cases'!$B:$B,$A15) -> 4 | C15: =COUNTIFS('Test Cases'!$B:$B,$A15,'Test Cases'!$L:$L,"Pass") -> 0 | D15: =COUNTIFS('Test Cases'!$B:$B,$A15,'Test Cases'!$L:$L,"Fail") -> 0 | E15: =COUNTIFS('Test Cases'!$B:$B,$A15,'Test Cases'!$L:$L,"Not run") -> 4 | F15: =IF(C15+D15=0,"-",C15/(C15+D15)) -> -
... A18: Subscription | B18: =COUNTIFS('Test Cases'!$B:$B,$A18) -> 5 | C18: =COUNTIFS('Test Cases'!$B:$B,$A18,'Test Cases'!$L:$L,"Pass") -> 0 | D18: =COUNTIFS('Test Cases'!$B:$B,$A18,'Test Cases'!$L:$L,"Fail") -> 0 | E18: =COUNTIFS('Test Cases'!$B:$B,$A18,'Test Cases'!$L:$L,"Not run") -> 5 | F18: =IF(C18+D18=0,"-",C18/(C18+D18)) -> -
A19: Total | B19: =SUM(B4:B18) -> 96 | C19: =SUM(C4:C18) -> 0 | D19: =SUM(D4:D18) -> 0 | E19: =SUM(E4:E18) -> 96 | F19: =IF(C19+D19=0,"-",C19/(C19+D19)) -> -
A21: By source
A22: Postman | B22: =COUNTIFS('Test Cases'!$M:$M,$A22) -> 58
A23: Added (not in Postman yet) | B23: =COUNTIFS('Test Cases'!$M:$M,$A23) -> 23
A24: Added (negative / security) | B24: =COUNTIFS('Test Cases'!$M:$M,$A24) -> 15
A26: How to use: run each request in Postman, type the status code you got in 'Actual status' and pick Pass or Fail in 'Result' on the Test Cases sheet. This sheet updates by itself.
A27: Tests marked 'Added' are not in your Postman collection yet. Add them there too so the collection and this file match.
A28: Expected status codes are assumed from the endpoint documents, so change them if your controllers return different codes.

Sheet Issues Found
A1: Issues found while reading the Postman collection
A3: # | B3: Area | C3: Issue | D3: Suggested fix | E3: Severity
A4: 1 | B4: Security | C4: Public signup accepts a role field. Someone could register as an admin. | D4: Ignore or reject the role on /auth/signup, or allow only store roles. | E4: High
A5: 2 | B5: Security | C5: Admin dashboard requests use a cashier token. | D5: Test with an admin token and add a 403 case for cashiers. | E5: High
A6: 3 | B6: Authorization | C6: Recent orders uses a cashier token, but docs allow only branch manager and branch admin. | D6: Test with a branch manager token, and a cashier should get 403. | E6: Medium
A7: 4 | B7: Collection | C7: Leftover requests from another project: login OTP on port 5454, keycloak profile, access token from refresh token, plus empty 'New Request' items. | D7: Delete them from the collection. | E7: Medium
A8: 5 | B8: Frontend / API | C8: Shift start: Postman sends a branch JSON body, frontend sends ?branchId=. | D8: Check the controller and make both match. | E8: Medium
A9: 6 | B9: Frontend / API | C9: Refund date range: Postman uses startDate/endDate, frontend uses from/to. | D9: Check the controller and make both match. | E9: Medium
A10: 7 | B10: Orders | C10: Frontend cart adds 18% tax, the order request has no tax field. | D10: Confirm the saved totalAmount matches what the bill shows. | E10: Medium
A11: 8 | B11: Collection | C11: Several GET requests carry a request body, and daily-sales sends an extra branchId header. | D11: Remove them. | E11: Low
A12: 9 | B12: Collection | C12: IDs like 52, 102 and 203 are hardcoded, and the folder is named 'AminDashboard'. | D12: Use collection variables and fix the typo. | E12: Low
A13: 10 | B13: Collection | C13: No request has tests or saved example responses. | D13: Add pm.test checks for status code and key fields, and save example responses. | E13: Medium
